MANIFEST.in
setup.py
b2gpopulate/__init__.py
b2gpopulate/b2gpopulate.py
b2gpopulate/resources/IMG_0001.jpg
b2gpopulate/resources/MUS_0001.mp3
b2gpopulate/resources/VID_0001.3gp
b2gpopulate/resources/calendarDb.zip
b2gpopulate/resources/contactsDb.zip
b2gpopulate/resources/contactsPictures.zip
b2gpopulate/resources/dialerDb.zip
b2gpopulate/resources/smsAttachments.zip
b2gpopulate/resources/smsDb.zip
b2gpopulate_v2.0.egg-info/PKG-INFO
b2gpopulate_v2.0.egg-info/SOURCES.txt
b2gpopulate_v2.0.egg-info/dependency_links.txt
b2gpopulate_v2.0.egg-info/entry_points.txt
b2gpopulate_v2.0.egg-info/not-zip-safe
b2gpopulate_v2.0.egg-info/requires.txt
b2gpopulate_v2.0.egg-info/top_level.txt